how_to_sea_auth_grpc/__init__.py
how_to_sea_auth_grpc/client.py
how_to_sea_auth_grpc/server.py
how_to_sea_auth_grpc/utils.py
how_to_sea_auth_grpc/__internal__/AuthTokenValidation_pb2.py
how_to_sea_auth_grpc/__internal__/AuthTokenValidation_pb2.pyi
how_to_sea_auth_grpc/__internal__/AuthTokenValidation_pb2_grpc.py
How_To_Sea_PyPackages-0.0.9.dist-info/METADATA
How_To_Sea_PyPackages-0.0.9.dist-info/WHEEL
How_To_Sea_PyPackages-0.0.9.dist-info/top_level.txt
How_To_Sea_PyPackages-0.0.9.dist-info/RECORD
