Metadata-Version: 2.1
Name: How-To-Sea-PyPackages
Version: 0.0.9
Summary: A internal project to easily access the GRPC bindings for the How to Sea project
Author-email: Jun Song <justin.warambourg@gmail.com>
Project-URL: Homepage, https://github.com/early-riser18/HowToSea
Project-URL: Issues, https://github.com/early-riser18/HowToSea/issues
Requires-Python: >=3.8
